README.md
setup.py
quantorxs/__init__.py
quantorxs/cli.py
quantorxs/gui_tk.py
quantorxs/io.py
quantorxs/main.py
quantorxs.egg-info/PKG-INFO
quantorxs.egg-info/SOURCES.txt
quantorxs.egg-info/dependency_links.txt
quantorxs.egg-info/entry_points.txt
quantorxs.egg-info/requires.txt
quantorxs.egg-info/top_level.txt
quantorxs/data/Carbonf2.f1f2
quantorxs/data/Nitrogenf2.f1f2
quantorxs/data/Oxygenf2.f1f2
quantorxs/data/example_spectra/PEEK.txt
quantorxs/data/example_spectra/PES_S2.txt
quantorxs/data/example_spectra/PLA-CO_S2.txt
quantorxs/data/example_spectra/nebulotron.txt
quantorxs/data/images/quantorxs_logo.gif
quantorxs/tests/__init__.py