Metadata-Version: 1.1
Name: quantorxs
Version: 0.1.1
Summary: XANES quantification of functional group abundances
Home-page: https://github.com/corentinlg/quantorxs
Author: Corentin Le Guillou
Author-email: corentin.le-guillou@univ-lille1.fr
License: GPLv3
Keywords: XANES abundance quantification
Platform: UNKNOWN
Classifier: Programming Language :: Python :: 3
Classifier: Development Status :: 4 - Beta
Classifier: Environment :: Console
Classifier: Intended Audience :: Science/Research
Classifier: License :: OSI Approved :: GNU General Public License v3 (GPLv3)
Classifier: Natural Language :: English
Classifier: Operating System :: OS Independent
Classifier: Topic :: Scientific/Engineering
Classifier: Topic :: Scientific/Engineering :: Physics
